{
  "siswa": [
    {
      "id": 1601825907099,
      "nisn": "0028897177",
      "nama": "Jansen Manuel",
      "tempat_lahir": "Jakarta",
      "tanggal_lahir": "2002-07-01",
      "jenis_kelamin": "Laki-Laki",
      "agama": "Kristen",
      "alamat": "Palmerah, Jakarta Barat"
    },
    {
      "id": 1601826040167,
      "nisn": "0028897178",
      "nama": "Manuel Jansen",
      "tempat_lahir": "Jakarta ",
      "tanggal_lahir": "2020-07-01",
      "jenis_kelamin": "Laki-Laki",
      "agama": "Kristen",
      "alamat": "Tangerang Selatan"
    },
    {
      "id": 1601826180855,
      "nisn": "1234567890",
      "nama": "Jansen Manuel",
      "tempat_lahir": "Rumah Sakit",
      "tanggal_lahir": "2001-01-01",
      "jenis_kelamin": "Laki-Laki",
      "agama": "Kristen",
      "alamat": "Rumah"
    },
    {
      "id": 1601859880556,
      "nisn": "0028897177",
      "nama": "Jansen Manuel",
      "tempat_lahir": "Jakarta",
      "tanggal_lahir": "2002-07-01",
      "jenis_kelamin": "Perempuan",
      "agama": "Islam",
      "alamat": "Jakarta"
    }
  ]
}